<?xml version="1.0" encoding="utf-8"?>
<SonarProjectConfig xmlns:xsi="http://www.w3.org/2001/XMLSchema-instance" xmlns:xsd="http://www.w3.org/2001/XMLSchema" xmlns="http://www.sonarsource.com/msbuild/analyzer/2021/1">
  <AnalysisConfigPath>I:\Facultate\Ergo\Ergo\Backend\.sonarqube\conf\SonarQubeAnalysisConfig.xml</AnalysisConfigPath>
  <ProjectPath>I:\Facultate\Ergo\Ergo\Backend\Ergo.Domain.Tests\Ergo.Domain.Tests.csproj</ProjectPath>
  <FilesToAnalyzePath>I:\Facultate\Ergo\Ergo\Backend\.sonarqube\conf\1\FilesToAnalyze.txt</FilesToAnalyzePath>
  <OutPath>I:\Facultate\Ergo\Ergo\Backend\.sonarqube\out\1</OutPath>
  <ProjectType>Test</ProjectType>
  <TargetFramework>net8.0</TargetFramework>
</SonarProjectConfig>